cricnotifier/__init__.py
cricnotifier/main.py
cricnotifier/static/icon/cricNotifier.ico
cricnotifier/static/icon/cricNotifier.png
cricnotifier-2.0.5.dist-info/entry_points.txt
cricnotifier-2.0.5.dist-info/LICENSE
cricnotifier-2.0.5.dist-info/WHEEL
cricnotifier-2.0.5.dist-info/METADATA
cricnotifier-2.0.5.dist-info/RECORD
