Metadata-Version: 2.1
Name: cricnotifier
Version: 2.0.5
Summary: A cli application for real time cricket match notifications.
Author: Jeet Jain
Author-email: jeet88833@gmail.com
Requires-Python: >=3.6,<4.0
Classifier: Programming Language :: Python :: 3
Classifier: Programming Language :: Python :: 3.6
Classifier: Programming Language :: Python :: 3.7
Classifier: Programming Language :: Python :: 3.8
Classifier: Programming Language :: Python :: 3.9
Classifier: Programming Language :: Python :: 3.10
Requires-Dist: PyYAML
Requires-Dist: beautifulsoup4
Requires-Dist: lxml
Requires-Dist: plyer
Requires-Dist: pytest
Requires-Dist: requests
Requires-Dist: rich
Requires-Dist: tabulate
Requires-Dist: typer[all] (>=0.6.1,<0.7.0)
Requires-Dist: win10toast
